JsonEnv/__init__.py
JsonEnv/jsonenv.py
JsonEnv-0.3.0.dist-info/LICENSE
JsonEnv-0.3.0.dist-info/METADATA
JsonEnv-0.3.0.dist-info/WHEEL
JsonEnv-0.3.0.dist-info/top_level.txt
JsonEnv-0.3.0.dist-info/RECORD
