Metadata-Version: 2.1
Name: JsonEnv
Version: 0.3.0
Summary: JsonEnv allows you to make environment variables with Json, allowing you to write numbers and other types of variables
Home-page: https://github.com/Greem3/JsonEnv
Author: Greem3
Author-email: Greem <ianpichardo575@gmail.com>
Project-URL: GitHub, https://github.com/Greem3/JsonEnv
Classifier: Programming Language :: Python :: 3
Classifier: License :: OSI Approved :: MIT License
Classifier: Operating System :: OS Independent
Requires-Python: >=3.8
License-File: LICENSE
